app.py
cli/__init__.py
cli/cli.py
core/formatting.py
core/termclock.py
tui/__init__.py
tui/countdown.py
tui/stopwatch.py
tui/theme.tcss
time_manager-0.2.25.dist-info/METADATA
time_manager-0.2.25.dist-info/WHEEL
time_manager-0.2.25.dist-info/entry_points.txt
time_manager-0.2.25.dist-info/licenses/LICENSE
time_manager-0.2.25.dist-info/RECORD
