Metadata-Version: 2.4
Name: time-manager
Version: 0.2.25
Summary: A terminal based stopwatch and countdown timer
License-File: LICENSE
Requires-Python: >=3.10
Requires-Dist: textual<6.12.0,>=6.11.0
Requires-Dist: typer>=0.21.0
